[
   {
       "_id":"1",
       "title":"Tech Conference",
       "organizer1": "Akshaya",
       "organizer2": "Anthara",
       "mobile1": "tel:9848827771",
       "mobile2": "tel:7799127165",
       "razorpayLink": " "
    },
    {
      "_id":"2",
      "title":"Poster Presentation",
      "organizer1": "G.Mounika",
      "organizer2": "Ch. Akshaya",
      "mobile1": "tel:8688745958",
      "mobile2": "tel:9392332554",
      "razorpayLink": " "
   },
   {
       "_id":"3",
       "title":"Quiz Time (Tech Quiz)",
       "organizer1": "Raja sai",
       "organizer2": "B. Anitha",
       "mobile1": "tel:8919750454",
       "mobile2": "tel:6303275438",
       "razorpayLink": " "
    },
    {
       "_id":"4",
       "title":"Content Writing",
       "organizer1": "D. Anjali",
       "organizer2": "G. Swapna",
       "mobile1": "tel:9959665177",
       "mobile2": "tel: ",
       "razorpayLink": " "
    },
   {
       "_id":"5",
       "title":"Paper Presentation",
       "organizer1": "B. Keerthi reddy",
       "organizer2": "J. Anjali",
       "organizer3": "E. Poojitha",
       "mobile1": "tel:8978143948",
       "mobile2": "tel:9346191737",
       "mobile3": "tel:6305547332",
       "razorpayLink": " "
    },
    {
      "_id":"6",
      "title":"Elocution",
      "organizer1": "M. Madhavi",
      "organizer2": "G. Vidhya sri",
      "organizer3": "V. Srija Deepthi",
      "mobile1": "tel:9849673083",
      "mobile2": "tel:7396775136",
      "mobile3": "tel:8247202843",
      "razorpayLink": " "
   },
   {
      "_id":"7",
      "title":"Circuitronics",
      "organizer1": "D.SV Sravan",
      "organizer2": "D. Puneeth",
      "mobile1": "tel:9985359532",
      "mobile2": "tel:6300885591",
      "razorpayLink": " "
   },
   {
      "_id":"8",
      "title":"Alighting talk",
      "organizer1": "E. Hepsiba",
      "organizer2": "M. Deepthi",
      "mobile1": "tel:9177188313",
      "mobile2": "tel:7569801175",
      "razorpayLink": " "
   },
   {
      "_id":"9",
      "title":"Aplos Coding",
      "organizer1": "P. Bhavana",
      "organizer2": "Ch. Navyasri",
      "mobile1": "tel:7993409047",
      "mobile2": "tel:",
      "razorpayLink": " "
   }
]
